py_chatgpt_plus/__init__.py
py_chatgpt_plus/main.py
py_chatgpt_plus/core/__init__.py
py_chatgpt_plus/core/chat_base.py
py_chatgpt_plus/core/chat_gpt_3.py
py_chatgpt_plus/core/image_gpt.py
py_chatgpt_plus/core/tests/__init__.py
py_chatgpt_plus/core/tests/chat_gpt_v3.py
py_chatgpt_plus/core/tests/image_gpt.py
py_chatgpt_plus/errors/__init__.py
py_chatgpt_plus/errors/error.py
py_chatgpt_plus/errors/export.py
py_chatgpt_plus/routes/__init__.py
py_chatgpt_plus/routes/api.py
py_chatgpt_plus/routes/chat_route.py
py_chatgpt_plus/routes/export.py
py_chatgpt_plus/routes/image_route.py
py_chatgpt_plus/services/__init__.py
py_chatgpt_plus/services/chat.py
py_chatgpt_plus/services/chat_ws.py
py_chatgpt_plus/utils/__init__.py
py_chatgpt_plus/utils/base_utils.py
py_chatgpt_plus/utils/conf.py
py_chatgpt_plus/utils/http_call.py
py_chatgpt_plus-0.2.0.dist-info/METADATA
py_chatgpt_plus-0.2.0.dist-info/WHEEL
py_chatgpt_plus-0.2.0.dist-info/top_level.txt
py_chatgpt_plus-0.2.0.dist-info/RECORD
