Metadata-Version: 2.1
Name: py-chatgpt-plus
Version: 0.2.0
Summary: Python chatgpt api
Home-page: https://github.com/rosemary666/chatgpt
Author: rosemary666
Author-email: 
License: Apache License 2.0
Platform: UNKNOWN
Classifier: Development Status :: 3 - Alpha
Classifier: License :: OSI Approved :: Apache Software License
Classifier: Operating System :: OS Independent
Classifier: Operating System :: MacOS :: MacOS X
Classifier: Operating System :: POSIX :: Linux
Classifier: Programming Language :: Python
Classifier: Programming Language :: Python :: 3
Classifier: Programming Language :: Python :: 3 :: Only
Classifier: Programming Language :: Python :: 3.7
Classifier: Programming Language :: Python :: 3.8
Classifier: Programming Language :: Python :: 3.9
Classifier: Programming Language :: Python :: 3.10
Classifier: Programming Language :: Python :: 3.11
Classifier: Programming Language :: Python :: Implementation :: CPython
Requires-Python: >=3.7
Requires-Dist: Flask (==2.2.3)
Requires-Dist: flask-restx (==1.1.0)
Requires-Dist: loguru (==0.6.0)
Requires-Dist: pytablewriter (==0.64.2)
Requires-Dist: PyYAML (==6.0)
Requires-Dist: requests (==2.28.1)
Requires-Dist: setuptools (==65.5.1)
Requires-Dist: websockets (==10.4)
